ASA_POST.py
AmpliconSuiteAggregator.py
AmpliconSuiteAggregatorFunctions.py
ampliconsuiteaggregator-2.1.3.dist-info/licenses/LICENSE
ampliconsuiteaggregator-2.1.3.dist-info/METADATA
ampliconsuiteaggregator-2.1.3.dist-info/WHEEL
ampliconsuiteaggregator-2.1.3.dist-info/top_level.txt
ampliconsuiteaggregator-2.1.3.dist-info/RECORD
