Metadata-Version: 2.4
Name: AmpliconSuiteAggregator
Version: 2.1.3
Summary: Aggregator tool for multiple Amplicon Architect outputs
Author-email: Edwin Huang <edwin5588@gmail.com>, Thorin Tabor <tmtabor@cloud.ucsd.edu>
License: ----------------------------------------------------------------
Project-URL: Homepage, https://github.com/AmpliconSuite/AmpliconSuiteAggregator
Project-URL: Issues, https://github.com/AmpliconSuite/AmpliconSuiteAggregator/issues
Classifier: Programming Language :: Python :: 3
Classifier: License :: OSI Approved :: MIT License
Classifier: Operating System :: OS Independent
Requires-Python: >3.7
License-File: LICENSE
Dynamic: license-file
